[
  {
    "file": "C:\\Users\\kvo\\Desktop\\lpbunified-master\\spring\\lima\\lima-server\\src\\main\\java\\be\\schaubroeck\\lpb\\rkm\\rekenmotor\\bruto\\VerwerkPrestaties.java",
    "class_name": "VerwerkPrestaties",
    "chunk_index": 0,
    "total_chunks": 1,
    "content": "package be.schaubroeck.lpb.rkm.rekenmotor.bruto;\n\nimport be.schaubroeck.lpb.rkm.rekenmotor.LoonElementVerwerker;\nimport be.schaubroeck.lpb.rkm.rekenmotor.RekenContext;\nimport be.schaubroeck.lpb.rkm.rekenmotor.RekenTijd;\nimport be.schaubroeck.lpb.rkm.rekenmotor.SleutelGegevens;\nimport be.schaubroeck.lpb.rkm.rekenmotor.keys.RekenChainKey;\nimport be.schaubroeck.lpb.rkm.rekenmotor.keys.UitzPerUurModus;\nimport be.schaubroeck.lpb.rkm.rekenmotor.util.AantalKalenderDagen;\nimport be.schaubroeck.lpb.rkm.rekenmotor.util.AantalRszDagen;\nimport be.schaubroeck.lpb.rkm.rekenmotor.util.ConstantManager;\nimport be.schaubroeck.lpb.rkm.rekenmotor.util.LoonCodeManager;\nimport be.schaubroeck.lpb.rkm.rekenmotor.util.LoonElementManager;\nimport be.schaubroeck.lpb.rkm.rekenmotor.util.MoneyMap;\nimport be.schaubroeck.lpb.rkm.rekenmotor.util.PrestatieSamenvatting;\nimport be.schaubroeck.lpb.rkm.rekenmotor.util.RegulManager;\nimport be.schaubroeck.lpb.tools.AardKodeExtensie;\nimport be.schaubroeck.lpb.tools.Opper;\nimport be.schaubroeck.lpb.tools.WeddeBerekening;\nimport be.schaubroeck.lpb.tools.enumtypes.Maandverwerking;\nimport be.schaubroeck.lpb.tools.enumtypes.RekenControleCode;\n\nimport java.math.BigDecimal;\n\nimport static be.schaubroeck.lpb.rkm.rekenmotor.keys.RekenChainKey.LOONCODE_GEWOON_LOON_KEY;\nimport static be.schaubroeck.lpb.rkm.rekenmotor.keys.RekenChainKey.UITZONDERLIJK_PER_UUR_KEY;\n\npublic class VerwerkPrestaties {\n\n    private static final String WAARSCHUWING_NOEMER_PLANNINGSUREN_ZERO = \"planningsuren met noemer 0 herleid naar dertigsten\";\n\n    private final Disponibiliteit disponibiliteit;\n    private final PrestatiesGewoneBezoldiging prestatiesGewoneBezoldiging;\n    private final PrestatiesDisponibiliteit prestatiesDisponibiliteit;\n    private final PrestatiesEuropeseVakantie prestatiesEuropeseVakantie;\n    private final PrestatiesZiekte prestatiesZiekte;\n    private final PrestatiesGewaarborgdLoon100PctOfDispo prestatiesGewaarborgdLoon100PctOfDispo;\n    private final PrestatiesDeeltijdseWerkhervatting prestatiesDeeltijdseWerkhervatting;\n\n    public VerwerkPrestaties(ConstantManager constantManager, LoonElementVerwerker loonElementVerwerker) {\n        this.disponibiliteit = new Disponibiliteit(constantManager);\n        this.prestatiesGewoneBezoldiging = new PrestatiesGewoneBezoldiging(constantManager, loonElementVerwerker, disponibiliteit);\n        this.prestatiesDisponibiliteit = new PrestatiesDisponibiliteit(loonElementVerwerker, disponibiliteit);\n        this.prestatiesEuropeseVakantie = new PrestatiesEuropeseVakantie(constantManager, loonElementVerwerker);\n        this.prestatiesZiekte = new PrestatiesZiekte(constantManager, loonElementVerwerker);\n        this.prestatiesGewaarborgdLoon100PctOfDispo = new PrestatiesGewaarborgdLoon100PctOfDispo(loonElementVerwerker);\n        this.prestatiesDeeltijdseWerkhervatting =\n                new PrestatiesDeeltijdseWerkhervatting(loonElementVerwerker, prestatiesDisponibiliteit, disponibiliteit);\n    }\n\n    public void verwerk(RekenContext context, SleutelGegevens aggregaat, MoneyMap<AardKodeExtensie> carryoverMap) {\n        for (Opper opper : aggregaat.getOppers()) {\n            verwerk(context, opper, carryoverMap);\n        }\n    }\n\n    private void verwerk(RekenContext context, Opper opper, MoneyMap<AardKodeExtensie> carryoverMap) {\n        LoonElementManager manager = context.getLoonElementManager();\n        LoonCodeManager loonCodeManager = context.getLoonCodeManager();\n        RekenTijd rekenTijd = context.getRekenTijd();\n        AardKodeExtensie looncodeGewoonLoon = context.getUnchecked(LOONCODE_GEWOON_LOON_KEY);\n\n        PrestatieSamenvatting samenvatting = context.getDoubleKey(RekenChainKey.PRESTATIE_SAMENVATTING_KEY, opper);\n        BigDecimal prestatieNoemer = getPrestatieNoemer(opper, rekenTijd, samenvatting);\n        UitzPerUurModus uitzPerUurModus = context.getUnchecked(UITZONDERLIJK_PER_UUR_KEY);\n        if (uitzPerUurModus != null && uitzPerUurModus != UitzPerUurModus.GEEN) {\n            PrestatieSamenvatting samenvattingPerUur = context.getDoubleKey(RekenChainKey.PRESTATIE_SAMENVATTING_UIT_PER_UUR_KEY, opper);\n            // todo hier voor de volgende fase\n            BigDecimal prestatieNoemerPerUur = samenvattingPerUur.getTotaalAantalUren();\n            if (prestatieNoemerPerUur.signum() != 0) {\n                samenvatting = samenvattingPerUur;\n                prestatieNoemer = prestatieNoemerPerUur;\n            } else {\n                RegulManager regulManager = context.getRegulManager();\n                regulManager.addProtoWaarschuwing(opper.getOpdracht(), RekenControleCode.PLANNINGSUREN_NOEMER_ZERO, WAARSCHUWING_NOEMER_PLANNINGSUREN_ZERO);\n            }\n        }\n\n        if (prestatieNoemer.signum() != 0) {\n            prestatiesGewoneBezoldiging.verwerk(manager, loonCodeManager, rekenTijd, looncodeGewoonLoon, samenvatting, prestatieNoemer, opper,\n                    carryoverMap);\n            prestatiesEuropeseVakantie.verwerk(manager, loonCodeManager, rekenTijd, samenvatting, prestatieNoemer, opper, carryoverMap);\n            prestatiesZiekte.verwerk(manager, loonCodeManager, rekenTijd, looncodeGewoonLoon, samenvatting, prestatieNoemer, opper, carryoverMap);\n            prestatiesGewaarborgdLoon100PctOfDispo.verwerk(manager, rekenTijd, samenvatting, prestatieNoemer, opper, carryoverMap);\n            prestatiesDisponibiliteit.verwerk(manager, loonCodeManager, rekenTijd, looncodeGewoonLoon, samenvatting, prestatieNoemer, opper, carryoverMap);\n            prestatiesDeeltijdseWerkhervatting.verwerk(manager, loonCodeManager, rekenTijd, looncodeGewoonLoon, samenvatting, prestatieNoemer, opper, carryoverMap);\n        }\n    }\n\n    private BigDecimal getPrestatieNoemer(Opper opper, RekenTijd rekenTijd, PrestatieSamenvatting samenvatting) {\n        WeddeBerekening weddeBerekening = opper.getWeddeBerekening();\n        Maandverwerking maandNaarDag = weddeBerekening.getOmzettingLoonMaandNaarDag();\n        switch (maandNaarDag) {\n            case DERTIGSTEN:\n            case PLANNINGSUREN:\n                return new BigDecimal(\"30\");\n            case RSZDAGEN:\n                return AantalRszDagen.inMaand(opper, rekenTijd.rekenPeriode);\n            case KALENDERDAGEN:\n                return AantalKalenderDagen.inMaand(rekenTijd.rekenPeriode);\n            case VARIABELE_RSZ_DAGEN:\n            case VLAAMSE_GEMEENSCHAP:\n                return samenvatting.getWerkDagen();\n            default:\n                return BigDecimal.ONE;\n        }\n    }\n}\n",
    "tokens": 1626
  }
]