[
  {
    "file": "C:\\Users\\kvo\\Desktop\\lpbunified-master\\spring\\lima\\lima-server\\src\\main\\java\\be\\schaubroeck\\lpb\\rkm\\rekenmotor\\rsz\\dmfappl\\IsPool2TerDmfappl.java",
    "class_name": "IsPool2TerDmfappl",
    "chunk_index": 0,
    "total_chunks": 1,
    "content": "package be.schaubroeck.lpb.rkm.rekenmotor.rsz.dmfappl;\n\nimport be.schaubroeck.lpb.rkm.rekenmotor.rsz.IsPool2Ter;\nimport be.schaubroeck.lpb.rkm.rekenmotor.util.ConstantManager;\nimport be.schaubroeck.lpb.tools.Constant;\nimport be.schaubroeck.lpb.tools.enumtypes.Konstanten;\nimport be.schaubroeck.lpb.tools.enumtypes.Pensioenstelsel;\nimport be.schaubroeck.lpb.tools.enumtypes.WerkgeversCategorie;\nimport be.schaubroeck.lpb.tools.rsz.CategorieKengetalStatuutPensioenstelsel;\nimport lombok.AllArgsConstructor;\nimport org.joda.time.LocalDate;\n\n@AllArgsConstructor\npublic class IsPool2TerDmfappl implements IsPool2Ter {\n\n    private final ConstantManager constantManager;\n\n    public boolean check(CategorieKengetalStatuutPensioenstelsel categorieKengetalStatuutPensioenstelsel, LocalDate zoekDatum) {\n        Constant pool2terConstante = constantManager.getByCodeDatumSafe(Konstanten.KST_POOL2TER.getCode(), zoekDatum);\n        boolean isPool2ter = pool2terConstante.getJaneen();\n        return isPool2ter && isPool2ter(categorieKengetalStatuutPensioenstelsel);\n    }\n\n    private boolean isPool2ter(CategorieKengetalStatuutPensioenstelsel categorieKengetalStatuutPensioenstelsel) {\n        WerkgeversCategorie werkgeversCategorie = categorieKengetalStatuutPensioenstelsel.getWerkgeversCategorie();\n        Pensioenstelsel pensioenStelsel = categorieKengetalStatuutPensioenstelsel.getPensioenStelsel();\n        boolean isVSpExngPct = werkgeversCategorie == WerkgeversCategorie.V_SP_EXNH_PCT;\n        boolean isVastbenoemdenPensioenstelselNieuwAangsloten = werkgeversCategorie == WerkgeversCategorie.VASTBENOEMDEN_PENSIOENSTELSEL_NIEUW_AANGESLOTEN;\n\n        boolean isEigenRegime5 = pensioenStelsel == Pensioenstelsel.EIGEN_REGIME5;\n        boolean isOmobRegime10 = pensioenStelsel == Pensioenstelsel.OMOB_REGIME10;\n\n        boolean isReplaceThis = isVastbenoemdenPensioenstelselNieuwAangsloten || isVSpExngPct;\n        return (isReplaceThis && isEigenRegime5) || (isVSpExngPct && isOmobRegime10);\n    }\n\n\n}\n",
    "tokens": 500
  }
]